bkcrypto/__init__.py
bkcrypto/asymmetric/__init__.py
bkcrypto/asymmetric/ciphers/__init__.py
bkcrypto/asymmetric/ciphers/base.py
bkcrypto/asymmetric/ciphers/rsa.py
bkcrypto/asymmetric/ciphers/sm2.py
bkcrypto/asymmetric/configs.py
bkcrypto/asymmetric/interceptors.py
bkcrypto/asymmetric/options.py
bkcrypto/constants.py
bkcrypto/contrib/__init__.py
bkcrypto/contrib/basic/__init__.py
bkcrypto/contrib/basic/ciphers.py
bkcrypto/contrib/django/__init__.py
bkcrypto/contrib/django/ciphers.py
bkcrypto/contrib/django/fields.py
bkcrypto/contrib/django/init_configs.py
bkcrypto/contrib/django/selectors.py
bkcrypto/contrib/django/settings.py
bkcrypto/contrib/drf/__init__.py
bkcrypto/symmetric/__init__.py
bkcrypto/symmetric/ciphers/__init__.py
bkcrypto/symmetric/ciphers/aes.py
bkcrypto/symmetric/ciphers/base.py
bkcrypto/symmetric/ciphers/sm4.py
bkcrypto/symmetric/configs.py
bkcrypto/symmetric/interceptors.py
bkcrypto/symmetric/options.py
bkcrypto/types.py
bkcrypto/utils/__init__.py
bkcrypto/utils/base_interceptors.py
bkcrypto/utils/convertors.py
bkcrypto/utils/module_loding.py
bk_crypto_python_sdk-2.0.1.dist-info/LICENSE.txt
bk_crypto_python_sdk-2.0.1.dist-info/METADATA
bk_crypto_python_sdk-2.0.1.dist-info/WHEEL
bk_crypto_python_sdk-2.0.1.dist-info/RECORD
