Metadata-Version: 2.1
Name: bk-crypto-python-sdk
Version: 2.0.1
Summary: bk-crypto-python-sdk is a lightweight cryptography toolkit for Python applications based on Cryptodome / tongsuopy and other encryption libraries.
Author: TencentBlueKing
Author-email: contactus_bk@tencent.com
Requires-Python: >=3.8,<3.13
Classifier: Programming Language :: Python :: 3
Classifier: Programming Language :: Python :: 3.8
Classifier: Programming Language :: Python :: 3.9
Classifier: Programming Language :: Python :: 3.10
Classifier: Programming Language :: Python :: 3.11
Classifier: Programming Language :: Python :: 3.12
Requires-Dist: dacite (>=1.8.1,<2.0.0)
Requires-Dist: pycryptodomex (>=3.18.0,<4.0.0)
Requires-Dist: tongsuopy-crayon (>=1.0.2b5,<2.0.0)
Requires-Dist: wrapt (>=1.15.0,<2.0.0)
